{
  "pedido_id": 50,
  "tipo_pedido": "Retirada",
  "nome": "jhonatta",
  "telefone": "",
  "endereco": "",
  "data_hora": "23/07/2025 23:09",
  "valor_total": 38.0,
  "forma_pagamento": "Dinheiro",
  "troco_para": "R$ 50,00",
  "marmitas": [
    {
      "tamanho": "grande",
      "carne": "Strogonoff de Frango",
      "adicionais": [
        {
          "nome": "Ovo",
          "quantidade": 2
        },
        {
          "nome": "Almondegas",
          "quantidade": 2
        }
      ],
      "bebidas": [],
      "outros": [],
      "observacoes": "",
      "preco": 38
    }
  ],
  "troco": 12.0
}