{
  "pedido_id": 9,
  "tipo_pedido": "Retirada",
  "nome": "jhonatan",
  "telefone": "",
  "endereco": "",
  "data_hora": "24/07/2025 00:37",
  "valor_total": 116.6,
  "forma_pagamento": "Cartão",
  "troco_para": "",
  "marmitas": [
    {
      "tamanho": "grande",
      "carne": "bisteca",
      "adicionais": [
        {
          "nome": "Bife Grelhado",
          "quantidade": 3
        }
      ],
      "bebidas": [
        {
          "nome": "Suco Natural",
          "quantidade": 3,
          "preco": 10
        }
      ],
      "outros": [
        {
          "nome": "Bala Diversas",
          "quantidade": 3,
          "preco": 0.2
        },
        {
          "nome": "Diamante Negro",
          "quantidade": 1,
          "preco": 6
        }
      ],
      "observacao": "sadasd",
      "preco": 77.6
    },
    {
      "tamanho": "media",
      "carne": "Peito de Frango a Milanesa",
      "adicionais": [
        {
          "nome": "Bife Grelhado",
          "quantidade": 3
        }
      ],
      "bebidas": [],
      "outros": [],
      "observacao": "ssssss",
      "preco": 39
    }
  ],
  "troco": 0
}